[
  {
    "Title": "The Lord of the Rings: The Fellowship of the Ring",
    "Year": "2001",
    "Type": "movie",
    "imdbID": "3v7x8sekmsknueu0q1",
    "createdAt": "2021-04-23T14:29:36.168Z",
    "reviews": [
      {
        "comment": "A good movie",
        "rate": 4,
        "id": "3v7x8sekmsknuewk4e",
        "createdAt": "2021-04-23T14:31:34.622Z"
      },
      {
        "comment": "yep i like it",
        "rate": 5,
        "id": "3v7x8sekmsknuf0vy2",
        "createdAt": "2021-04-23T14:34:56.570Z"
      }
    ],
    "Poster": "http://localhost:5000/lord1.jpg",
    "lastUpdated": "2021-04-23T14:32:56.145Z"
  }
]
